yahalloLib/__init__.py
yahalloLib/base.py
yahalloLib/lib.py
yahalloLib/serialize.py
yahalloLib/utils/__init__.py
yahalloLib/utils/constants.py
yahalloLib/utils/helpers.py
yahalloLib/utils/templates.py
yahalloLib-1.0.0.dist-info/METADATA
yahalloLib-1.0.0.dist-info/WHEEL
yahalloLib-1.0.0.dist-info/entry_points.txt
yahalloLib-1.0.0.dist-info/top_level.txt
yahalloLib-1.0.0.dist-info/RECORD
