Metadata-Version: 2.1
Name: yahalloLib
Version: 1.0.0
Summary: IGI LAB3
Author: Daniil
